{
  "dayNumber": 1,
  "day": "Četrtek",
  "date": "22. junij",
  "activities": [
    {
      "date": "Četrtek, 22. junij",
      "time": "Cel dan",
      "location": "Borštnikov vrt",
      "price": 0,
      "title": "Slikarska kolonija",
      "eventType": "Delavnica",
      "highlighted": false,
      "eventLink": "/dogodki/day-2/slikarska-kolonija"
    },
    {
      "date": "Četrtek, 22. junij",
      "time": "13.00 - 14.00",
      "location": "Borštnikov hram",
      "price": 0,
      "title": "Kreativne delavnice",
      "eventType": "Delavnica",
      "highlighted": false,
      "eventLink": "/dogodki/day-2/kreativne-delavnice"
    },
    {
      "date": "Četrtek, 22. junij",
      "time": "14.00 - 18.00",
      "location": "Borštnikov hram",
      "price": 35,
      "priceStudents": 25,
      "title": "Delavnica s Tjašo Črnigoj",
      "eventType": "Delavnica",
      "highlighted": true,
      "eventLink": "/dogodki/day-2/delavnica-tjasa-crnigoj",
      "callToActionLink": "https://olaii.com/event/3092/festival-borstnikovanje-gledaliske-delavnice?ref=KSMUMVX",
      "callToActionTitle": "Nakup vstopnic"
    },
    {
      "date": "Četrtek, 22. junij",
      "time": "18.00 - 19.15",
      "location": "Pod Jenkovo lipo",
      "price": 0,
      "title": "Doživi Cerklje",
      "eventType": "Voden ogled",
      "highlighted": true,
      "eventLink": "/dogodki/day-2/dozivi-cerklje",
      "callToActionLink": "https://forms.gle/hKXyjGX9ArKdPxNr8",
      "callToActionTitle": "Prijava"
    },
    {
      "date": "Četrtek, 22. junij",
      "time": "20.00 - 21.30",
      "location": "Borštnikov hram",
      "price": 16,
      "priceStudents": 12,
      "title": "Predsednice",
      "eventType": "Predstava",
      "highlighted": true,
      "eventLink": "/dogodki/day-2/predsednice",
      "callToActionLink": "https://olaii.com/event/3086/festival-borstnikovanje-predsednice?ref=KSMUMVX",
      "callToActionTitle": "Nakup vstopnic"
    }
  ]
}
